MANIFEST.in
setup.py
dboptions/__init__.py
dboptions/admin.py
dboptions/apps.py
dboptions/forms.py
dboptions/models.py
dboptions/tests.py
dboptions/views.py
dboptions/migrations/0001_initial.py
dboptions/migrations/__init__.py
django_dboptions.egg-info/PKG-INFO
django_dboptions.egg-info/SOURCES.txt
django_dboptions.egg-info/dependency_links.txt
django_dboptions.egg-info/not-zip-safe
django_dboptions.egg-info/requires.txt
django_dboptions.egg-info/top_level.txt